[
  {
    "Author": "NostraThomas & Dragon",
    "Name": "Pocket Sized Universe",
    "InternalName": "PocketSizedUniverse",
    "Description": "This plugin will synchronize your Penumbra mods and other glam plugins with paired clients via robust P2P protocols.",
    "ApplicableVersion": "any",
    "DalamudApiLevel": 14,
    "TestingDalamudApiLevel": 13,
    "Tags": [
      "customization",
      "modding",
      "synchronization"
    ],
    "LoadRequiredState": 0,
    "LoadSync": false,
    "CanUnloadAsync": false,
    "LoadPriority": 0,
    "IsTestingExclusive": false,
    "IconUrl": "https://raw.githubusercontent.com/Pocket-Sized-Universe/PocketSizedUniverse/main/PocketSizedUniverse/images/icon.jpg",
    "Punchline": "We're beating a dead horse.",
    "AcceptsFeedback": true,
    "DownloadLinkInstall": "https://github.com/Pocket-Sized-Universe/PocketSizedUniverse/releases/download/0.5.2/PocketSizedUniverse.zip",
    "AssemblyVersion": "0.5.2",
    "DownloadLinkUpdate": "https://github.com/Pocket-Sized-Universe/PocketSizedUniverse/releases/download/0.5.2/PocketSizedUniverse.zip",
    "DownloadLinkTesting": "https://github.com/Pocket-Sized-Universe/PocketSizedUniverse/releases/download/0.5.0/PocketSizedUniverse.zip",
    "TestingAssemblyVersion": "0.5.0",
    "Changelog": "**Full Changelog**: https://github.com/Pocket-Sized-Universe/PocketSizedUniverse/compare/0.5.1...0.5.2",
    "DownloadCount": 1793
  }
]